inbs/__init__.py
inbs/__main__.py
inbs-0.0.4.dist-info/LICENSE
inbs-0.0.4.dist-info/METADATA
inbs-0.0.4.dist-info/WHEEL
inbs-0.0.4.dist-info/top_level.txt
inbs-0.0.4.dist-info/RECORD
