Metadata-Version: 2.1
Name: inbs
Version: 0.0.4
Summary: Flask based notebook server
Home-page: https://github.com/NelsonSharma/inbs
Author: Nelson.S
Author-email: mail.nelsonsharma@gmail.com
Classifier: License :: OSI Approved :: MIT License
License-File: LICENSE
